{
    "filename": "00028N.png",
    "tags": "bicycle, bicycle helmet, biker, cycle, dark, person, man, night, night view, pavement, ride, road",
    "tags_chinese": "\u81ea\u884c\u8f66 , \u81ea\u884c\u8f66\u5934\u76d4 , \u81ea\u884c\u8f66\u9a91\u58eb, \u81ea\u884c\u8f66, \u9ed1\u6697, \u4eba, \u7537\u4eba, \u665a\u4e0a , \u591c\u666f , \u4eba\u884c\u9053/\u786c\u8def\u9762, \u9a91/\u642d\u4e58, \u8def ",
    "predictions": [
        {
            "phrase": "bicycle(0.60)",
            "score": 0.6097540855407715,
            "box": [
                0.8024226427078247,
                0.5921025276184082,
                0.07070702314376831,
                0.1879008710384369
            ]
        },
        {
            "phrase": "bicycle helmet(0.56)",
            "score": 0.5679692625999451,
            "box": [
                0.8068022131919861,
                0.36056214570999146,
                0.03764891251921654,
                0.055245235562324524
            ]
        },
        {
            "phrase": "pavement(0.36)",
            "score": 0.3664827048778534,
            "box": [
                0.500083863735199,
                0.8080915808677673,
                0.9954742789268494,
                0.377247154712677
            ]
        },
        {
            "phrase": "man(0.50)",
            "score": 0.5051797032356262,
            "box": [
                0.804057776927948,
                0.4827330708503723,
                0.10172003507614136,
                0.2964322566986084
            ]
        },
        {
            "phrase": "biker(0.31)",
            "score": 0.31308701634407043,
            "box": [
                0.8041508197784424,
                0.48890605568885803,
                0.10250845551490784,
                0.309953510761261
            ]
        },
        {
            "phrase": "person(0.35)",
            "score": 0.3549414575099945,
            "box": [
                0.5346801280975342,
                0.49803411960601807,
                0.048973433673381805,
                0.17795807123184204
            ]
        },
        {
            "phrase": "road(0.33)",
            "score": 0.3379310965538025,
            "box": [
                0.5000334978103638,
                0.8081926107406616,
                0.9950173497200012,
                0.3775421380996704
            ]
        },
        {
            "phrase": "cycle(0.36)",
            "score": 0.3638632893562317,
            "box": [
                0.801903247833252,
                0.5920454859733582,
                0.07274124026298523,
                0.1884007453918457
            ]
        },
        {
            "phrase": "person(0.27)",
            "score": 0.27138713002204895,
            "box": [
                0.5716186761856079,
                0.5054054260253906,
                0.04314219579100609,
                0.16118530929088593
            ]
        },
        {
            "phrase": "pavement road(0.27)",
            "score": 0.2756613790988922,
            "box": [
                0.5000983476638794,
                0.7756470441818237,
                0.9949618577957153,
                0.4418094754219055
            ]
        }
    ]
}